{
  "entry": "server.js",
  "files": {
    "components/color-mode-switcher.js": "components/color-mode-switcher.js",
    "components/index-events-children-spring.js": "components/index-events-children-spring.js",
    "components/index-events-lovely-spring.js": "components/index-events-lovely-spring.js",
    "components/index-events-mid-autumn.js": "components/index-events-mid-autumn.js",
    "components/index-events-night-porridge.js": "components/index-events-night-porridge.js",
    "components/index-news-grid.js": "components/index-news-grid.js",
    "components/index-working-areas.js": "components/index-working-areas.js",
    "components/language-switcher.js": "components/language-switcher.js",
    "components/layout-alternate-menu.js": "components/layout-alternate-menu.js",
    "components/layout-footer.js": "components/layout-footer.js",
    "components/layout-header.js": "components/layout-header.js",
    "components/layout-lobby.js": "components/layout-lobby.js",
    "components/layout-mobile-menu.js": "components/layout-mobile-menu.js",
    "components/layout-scroll-top-button.js": "components/layout-scroll-top-button.js",
    "components/layout-topmost.js": "components/layout-topmost.js",
    "components/news-category-picker.js": "components/news-category-picker.js",
    "components/news-detail-meta.js": "components/news-detail-meta.js",
    "components/news-detail-related.js": "components/news-detail-related.js",
    "lang-en.js.js": "lang-en.js.js",
    "lang-vi.js.js": "lang-vi.js.js",
    "pages/about.js": "pages/about.js",
    "pages/contact.js": "pages/contact.js",
    "pages/gallery.js": "pages/gallery.js",
    "pages/index.js": "pages/index.js",
    "pages/members.js": "pages/members.js",
    "pages/news/_slug.js": "pages/news/_slug.js",
    "pages/news/p/_slug.js": "pages/news/p/_slug.js",
    "server.js": "server.js"
  },
  "maps": {
    "components/color-mode-switcher.js": "components/color-mode-switcher.js.map",
    "components/index-events-children-spring.js": "components/index-events-children-spring.js.map",
    "components/index-events-lovely-spring.js": "components/index-events-lovely-spring.js.map",
    "components/index-events-mid-autumn.js": "components/index-events-mid-autumn.js.map",
    "components/index-events-night-porridge.js": "components/index-events-night-porridge.js.map",
    "components/index-news-grid.js": "components/index-news-grid.js.map",
    "components/index-working-areas.js": "components/index-working-areas.js.map",
    "components/language-switcher.js": "components/language-switcher.js.map",
    "components/layout-alternate-menu.js": "components/layout-alternate-menu.js.map",
    "components/layout-footer.js": "components/layout-footer.js.map",
    "components/layout-header.js": "components/layout-header.js.map",
    "components/layout-lobby.js": "components/layout-lobby.js.map",
    "components/layout-mobile-menu.js": "components/layout-mobile-menu.js.map",
    "components/layout-scroll-top-button.js": "components/layout-scroll-top-button.js.map",
    "components/layout-topmost.js": "components/layout-topmost.js.map",
    "components/news-category-picker.js": "components/news-category-picker.js.map",
    "components/news-detail-meta.js": "components/news-detail-meta.js.map",
    "components/news-detail-related.js": "components/news-detail-related.js.map",
    "lang-en.js.js": "lang-en.js.js.map",
    "lang-vi.js.js": "lang-vi.js.js.map",
    "pages/about.js": "pages/about.js.map",
    "pages/contact.js": "pages/contact.js.map",
    "pages/gallery.js": "pages/gallery.js.map",
    "pages/index.js": "pages/index.js.map",
    "pages/members.js": "pages/members.js.map",
    "pages/news/_slug.js": "pages/news/_slug.js.map",
    "pages/news/p/_slug.js": "pages/news/p/_slug.js.map",
    "server.js": "server.js.map"
  }
}